ladm/__init__.py
ladm/main/generator_context.py
ladm/main/generator_strategy.py
ladm/main/main.py
ladm/main/util/custom_exceptions.py
ladm/main/util/types.py
ladm/tests/resources/correct-skill-ladm/requirements.txt
ladm/tests/resources/correct-skill-ladm/skill_with_dependencies.yml
ladm/tests/resources/correct-skill-ladm/skill_with_dependencies_empty.yml
ladm/tests/resources/correct-skill-ladm/skill_with_dependencies_libraries_only.yml
ladm/tests/resources/correct-skill-ladm/skill_with_dependencies_system_only.yml
ladm/tests/resources/correct-skill-ladm/skill_with_dependencies_with_data.yml
ladm/tests/resources/correct-skill-ladm/skill_with_dependencies_with_specified_language_java.yml
ladm/tests/resources/correct-skill-ladm/skill_without_dependencies.yml
ladm/tests/resources/correct-skill-ladm/src/contract/echo.dbs
ladm/tests/resources/correct-skill-ladm/src/handler.py
ladm/tests/resources/incorrect-skill-ladm/skill_with_dependencies_with_models_wrong_format.yml
ladm/tests/resources/incorrect-skill-ladm/skill_with_dependencies_with_specified_language_missing.yml
ladm/tests/resources/incorrect-skill-ladm/skill_with_dependencies_with_specified_language_unsupported.yml
ladm/tests/resources/incorrect-skill-ladm/src/contract/echo.dbs
ladm/tests/resources/incorrect-skill-ladm/src/handler.py
ladm/tests/test_ladm.py
ladm-0.1.4.dist-info/entry_points.txt
ladm-0.1.4.dist-info/WHEEL
ladm-0.1.4.dist-info/METADATA
ladm-0.1.4.dist-info/RECORD
